miniMLP/__init__.py
miniMLP/activation.py
miniMLP/engine.py
miniMLP/layers.py
miniMLP/losses.py
miniMLP/optimizers.py
miniMLP/regularizers.py
miniMLP/schedulers.py
miniMLP/utils.py
minimlp-0.1.1.dist-info/licenses/LICENSE
minimlp-0.1.1.dist-info/METADATA
minimlp-0.1.1.dist-info/WHEEL
minimlp-0.1.1.dist-info/top_level.txt
minimlp-0.1.1.dist-info/RECORD
