Metadata-Version: 2.4
Name: miniMLP
Version: 0.1.1
Summary: Implementation of very small scale Neural Network from scratch.
Home-page: https://github.com/neuralsorcerer/miniMLP
Author: Soumyadip Sarkar
Author-email: soumyadip@soumyadipsarkar.com
Classifier: Programming Language :: Python :: 3
Classifier: License :: OSI Approved :: MIT License
Classifier: Operating System :: OS Independent
Requires-Python: >=3.6
License-File: LICENSE
Dynamic: author
Dynamic: author-email
Dynamic: classifier
Dynamic: description
Dynamic: description-content-type
Dynamic: home-page
Dynamic: license-file
Dynamic: requires-python
Dynamic: summary
